setup.cfg
setup.py
PySCAD.egg-info/PKG-INFO
PySCAD.egg-info/SOURCES.txt
PySCAD.egg-info/dependency_links.txt
PySCAD.egg-info/requires.txt
PySCAD.egg-info/top_level.txt
src/__init__.py
src/base.py
src/color.py
src/colornames.py
src/core.py
src/drill.py
src/drill_sizes.py
src/gear.py
src/geometry.py
src/primitives.py
src/screw.py
src/text.py
src/threads.py
src/utils.py
src/vector.py