Metadata-Version: 1.1
Name: PySCAD
Version: 0.1
Summary: Python based OpenSCAD framework
Home-page: https://github.com/vishnubob/pyscad
Author: Giles Hall
Author-email: giles@polymerase.org
License: UNKNOWN
Download-URL: https://github.com/vishnubob/pyscad/archive/v0.1.zip
Keywords: scad,3D modeling,3D printing
Platform: UNKNOWN
Classifier: Development Status :: 3 - Alpha
Classifier: License :: OSI Approved :: MIT License
Classifier: Programming Language :: Python :: 2 :: Only
Classifier: Topic :: Multimedia :: Graphics :: 3D Modeling
Classifier: Topic :: Multimedia :: Graphics :: 3D Rendering
